data_slicer/__init__.py
data_slicer/cmaps.py
data_slicer/cutline.py
data_slicer/dataloading.py
data_slicer/dsviewbox.py
data_slicer/imageplot.py
data_slicer/model.py
data_slicer/pit.py
data_slicer/plugin.py
data_slicer/set_up_logging.py
data_slicer/utilities.py
data_slicer/widgets.py
data_slicer/data/brain.p
data_slicer/data/cmaps.p
data_slicer/data/kocean.cmap
data_slicer/data/neutrons.cmap
data_slicer/data/pit.p
data_slicer/data/rainbow_light.cmap
data_slicer/data/testdata_100_150_200.p
data_slicer/tests/__init__.py
data_slicer/tests/run_tests.py
data_slicer/tests/test_freeslice.py
data_slicer/tests/test_logging.py
data_slicer/tests/test_pit.py
data_slicer/tests/test_threedwidget.py
data_slicer-1.0.3.dist-info/LICENSE
data_slicer-1.0.3.dist-info/METADATA
data_slicer-1.0.3.dist-info/WHEEL
data_slicer-1.0.3.dist-info/entry_points.txt
data_slicer-1.0.3.dist-info/top_level.txt
data_slicer-1.0.3.dist-info/RECORD
