Metadata-Version: 2.1
Name: data-slicer
Version: 1.0.3
Summary: Tools for quick visualization of three dimensional datasets.
Home-page: https://github.com/kuadrat/data_slicer.git
Author: Kevin Kramer
Author-email: kevin.kramer@uzh.ch
License: UNKNOWN
Platform: UNKNOWN
Classifier: Programming Language :: Python :: 3
Classifier: License :: OSI Approved :: MIT License
Classifier: Operating System :: OS Independent
License-File: LICENSE
Requires-Dist: PyOpenGL (>=3.1.1a1)
Requires-Dist: PyQt5 (>=5.13.2)
Requires-Dist: matplotlib (>=3.1.1)
Requires-Dist: numpy (>=1.17.3)
Requires-Dist: pyqtgraph (>=0.11.0)
Requires-Dist: pytest-qt (>=3.3.0)
Requires-Dist: pytest (>=6.2.2)
Requires-Dist: qtconsole (>=4.6.0)
